LICENSE
README.md
setup.py
mindsdb_sql_parser/__about__.py
mindsdb_sql_parser/__init__.py
mindsdb_sql_parser/exceptions.py
mindsdb_sql_parser/lexer.py
mindsdb_sql_parser/logger.py
mindsdb_sql_parser/parser.json
mindsdb_sql_parser/parser.py
mindsdb_sql_parser/utils.py
mindsdb_sql_parser.egg-info/PKG-INFO
mindsdb_sql_parser.egg-info/SOURCES.txt
mindsdb_sql_parser.egg-info/dependency_links.txt
mindsdb_sql_parser.egg-info/top_level.txt
mindsdb_sql_parser/ast/__init__.py
mindsdb_sql_parser/ast/alter_table.py
mindsdb_sql_parser/ast/base.py
mindsdb_sql_parser/ast/commit_transaction.py
mindsdb_sql_parser/ast/create.py
mindsdb_sql_parser/ast/delete.py
mindsdb_sql_parser/ast/describe.py
mindsdb_sql_parser/ast/drop.py
mindsdb_sql_parser/ast/explain.py
mindsdb_sql_parser/ast/insert.py
mindsdb_sql_parser/ast/rollback_transaction.py
mindsdb_sql_parser/ast/set.py
mindsdb_sql_parser/ast/show.py
mindsdb_sql_parser/ast/start_transaction.py
mindsdb_sql_parser/ast/update.py
mindsdb_sql_parser/ast/use.py
mindsdb_sql_parser/ast/variable.py
mindsdb_sql_parser/ast/mindsdb/__init__.py
mindsdb_sql_parser/ast/mindsdb/agents.py
mindsdb_sql_parser/ast/mindsdb/alter_database.py
mindsdb_sql_parser/ast/mindsdb/alter_view.py
mindsdb_sql_parser/ast/mindsdb/chatbot.py
mindsdb_sql_parser/ast/mindsdb/create_database.py
mindsdb_sql_parser/ast/mindsdb/create_job.py
mindsdb_sql_parser/ast/mindsdb/create_ml_engine.py
mindsdb_sql_parser/ast/mindsdb/create_predictor.py
mindsdb_sql_parser/ast/mindsdb/create_view.py
mindsdb_sql_parser/ast/mindsdb/drop_dataset.py
mindsdb_sql_parser/ast/mindsdb/drop_datasource.py
mindsdb_sql_parser/ast/mindsdb/drop_job.py
mindsdb_sql_parser/ast/mindsdb/drop_ml_engine.py
mindsdb_sql_parser/ast/mindsdb/drop_predictor.py
mindsdb_sql_parser/ast/mindsdb/evaluate.py
mindsdb_sql_parser/ast/mindsdb/finetune_predictor.py
mindsdb_sql_parser/ast/mindsdb/knowledge_base.py
mindsdb_sql_parser/ast/mindsdb/latest.py
mindsdb_sql_parser/ast/mindsdb/retrain_predictor.py
mindsdb_sql_parser/ast/mindsdb/skills.py
mindsdb_sql_parser/ast/mindsdb/trigger.py
mindsdb_sql_parser/ast/select/__init__.py
mindsdb_sql_parser/ast/select/case.py
