Metadata-Version: 2.4
Name: mindsdb_sql_parser
Version: 0.13.3
Summary: Mindsdb SQL parser
Home-page: https://github.com/mindsdb/mindsdb_sql_parser
Download-URL: https://pypi.org/project/mindsdb_sql_parser
Author: MindsDB Inc
Author-email: jorge@mindsdb.com
License: MIT
Classifier: Programming Language :: Python :: 3
Classifier: Operating System :: OS Independent
Requires-Python: >=3.10
License-File: LICENSE
Dynamic: author
Dynamic: author-email
Dynamic: classifier
Dynamic: download-url
Dynamic: home-page
Dynamic: license
Dynamic: license-file
Dynamic: requires-python
Dynamic: summary
